<?xml version="1.0" ?>

<container xmlns="http://symfony.com/schema/dic/services"
           xmlns:xsi="http://www.w3.org/2001/XMLSchema-instance"
           xsi:schemaLocation="http://symfony.com/schema/dic/services http://symfony.com/schema/dic/services/services-1.0.xsd">

    <services>
        <service id="talkly.markdown.environment" class="League\CommonMark\Environment">
            <factory class="League\CommonMark\Environment" method="createCommonMarkEnvironment" />
            <call method="addInlineParser">
                <argument type="service" id="talkly.markdown.topic_parser"/>
            </call>
        </service>

        <service id="talkly.markdown" class="League\CommonMark\CommonMarkConverter">
            <argument type="collection"/>
            <argument type="service" id="talkly.markdown.environment"/>
        </service>

        <service id="talkly.markdown.topic_parser"
                 class="TobiasOlry\TalklyBundle\Markdown\TopicParser">
            <argument type="service" id="talkly.repository.topic"/>
            <argument type="service" id="router"/>
            <tag name="webuni_commonmark.extension"/>
        </service>

        <service id="talkly.twig.extension.markdown"
                 class="TobiasOlry\TalklyBundle\Twig\MarkdownExtension">
            <argument type="service" id="talkly.markdown"/>
            <tag name="twig.extension"/>
        </service>
    </services>
</container>